lte_nr_frequency/__init__.py
lte_nr_frequency-0.0.3.dist-info/METADATA
lte_nr_frequency-0.0.3.dist-info/WHEEL
lte_nr_frequency-0.0.3.dist-info/top_level.txt
lte_nr_frequency-0.0.3.dist-info/RECORD
