Metadata-Version: 2.1
Name: lte-nr-frequency
Version: 0.0.3
Summary: A python package to calculate the lte and nr frequency
Author-email: Rulin Xing <xingrulin@gmail.com>, Wang Xiang <ramwin@qq.com>
Project-URL: Homepage, https://github.com/aloha9876/LTE_NR_Frequency
Requires-Python: >=3.8
Requires-Dist: pandas
